twiss/__init__.py
twiss/convert.py
twiss/distribution.py
twiss/invariant.py
twiss/matrix.py
twiss/normal.py
twiss/transport.py
twiss/util.py
twiss/wolski.py
twiss-0.2.6.dist-info/LICENSE
twiss-0.2.6.dist-info/METADATA
twiss-0.2.6.dist-info/WHEEL
twiss-0.2.6.dist-info/top_level.txt
twiss-0.2.6.dist-info/RECORD
