Metadata-Version: 2.1
Name: twiss
Version: 0.2.6
Summary: Differentiable Wolski twiss matrices computation for arbitrary dimension stable symplectic matrices
Author: Ivan Morozov
License: MIT
Project-URL: documentation, https://i-a-morozov.github.io/twiss/
Project-URL: repository, https://github.com/i-a-morozov/twiss
Keywords: torch,twiss,differentiable,symplectic,matrix
Classifier: Development Status :: 4 - Beta
Classifier: Intended Audience :: Developers
Classifier: Natural Language :: English
Classifier: Programming Language :: Python :: 3
Classifier: Programming Language :: Python :: 3.10
Requires-Python: >=3.10
License-File: LICENSE
Requires-Dist: torch >=2.0.1
Provides-Extra: all
Requires-Dist: twiss[build,docs,examples,test] ; extra == 'all'
Provides-Extra: build
Requires-Dist: build ; extra == 'build'
Requires-Dist: setuptools ; extra == 'build'
Requires-Dist: twine ; extra == 'build'
Provides-Extra: docs
Requires-Dist: pandoc ; extra == 'docs'
Requires-Dist: sphinx-rtd-theme ; extra == 'docs'
Requires-Dist: ipykernel ; extra == 'docs'
Requires-Dist: nbsphinx ; extra == 'docs'
Provides-Extra: examples
Requires-Dist: jupyterlab ; extra == 'examples'
Requires-Dist: pandas ; extra == 'examples'
Requires-Dist: matplotlib ; extra == 'examples'
Requires-Dist: seaborn ; extra == 'examples'
Requires-Dist: ndmap ; extra == 'examples'
Provides-Extra: test
Requires-Dist: mypy ; extra == 'test'
Requires-Dist: pylint ; extra == 'test'
Requires-Dist: pytest ; extra == 'test'
Requires-Dist: pytest-cov ; extra == 'test'
Requires-Dist: numpy ; extra == 'test'
